{
    "title": "Asesor Comercial - Villa Ramallo (Bs As)",
    "business_name": "LS Group",
    "location": "Ramallo, Buenos Aires",
    "description": "¿Vivís en Ramallo o alrededores?Sumaremos un ASESOR COMERCIAL para el equipo de ventas de una empresa de Medicina Prepaga en Villa Ramallo, Buenos Aires.LS RRHH se encuentra en la búsqueda de personas con perfil comercial o relacional y experiencia en ventas / atención al cliente.Descripción:Sumaremos 1 vendedor, nos enfocamos en personas con:- Experiencia en ventas / atención al cliente (Excluyente)- Experiencia en venta de planes de salud (No Excluyente)- Ganas de trabajar y seriedad para cumplir con las tareas- Actitud aprendiente y positiva- Dinamismo y proactividad- Ganas de ser parte de una empresa con enfoque en el clienteEntre sus responsabilidades se encuentran:- Generar ventas mediante el asesoramiento según estándares de calidad en la localidad de Villa Ramallo y alrededores,- promover/ promocionar la importancia del cuidado de la salud con una empresa sólida y experta,- reporte diario de resultados,- participación de reuniones virtuales y presenciales,- participación en eventos de la marca para la generación de datos con valor comercial, entre otros.Requisitos Excluyentes:• Residir en la ciudad de Villa Ramallo.• Es excluyente no contar con habilidades de comunicación y relacionamiento desarrolladas.Capacitación constante.Esquema de comisiones adicionales.Tipo de contrato: PermanenteZona de Trabajo: Villa Ramallo y alrededores.Jornada de trabajo: Completa (Lunes a Viernes y eventualmente sábados medio día)¡TRANSFORMÁ TU EXPERIENCIA EN ÉXITO!TE CONECTAMOS CON PROYECTOS ESTIMULANTES PARA CAMBIAR TU VIDA.LS Recursos Humanos, somos una empresa de servicios para conectar lideres con oportunidades, todos nuestros clientes son empresas reales, serías y verificadas. No nos involucramos con propuestas que no sean serías ni sólidas.",
    "requirements": "Educación mínima: Secundaria2 años de experienciaEdad: entre 25 y 40 añosConocimientos: Trabajo en equipo, Microsoft excel, Microsoft office, Ventas, Atención al clienteDisponibilidad de viajar: Si"
}