{
    "title": "Analista de Recursos Humanos Sr",
    "business_name": "autradiocarxtreme",
    "location": "San Nicolás, Capital Federal",
    "description": "Analista de RRHH Sr.¿Tenés experiencia en Recursos Humanos en posiciones generalistas, podés trabajar en ambientes dinámicos y sos resolutiva/o?¡Te estamos buscando!Te invitamos a sumarte a un equipo con proyectos desafiantes y en constante crecimiento.ResponsabilidadesAdministrar el proceso de payroll, controlando el servicio externo de liquidación, asegurando la integridad de los datos y verificando el cumplimiento de todas las etapas del proceso, a fin de garantizar la correcta liquidación de haberes.Controlar la documentación referida al área.Administrar el sistema de control horario e inasistencias del personal.Gestionar la digitalización de legajos y recopilar toda la documentación pertinente de los colaboradores.Ser el nexo con los colaboradores y resolver sus consultas e inquietudes.Confeccionar reportes e indicadores de gestión.Colaborar en la ejecución de programas de capacitación y planes de desarrollo.Gestionar los procesos de onboarding y offboarding.Desarrollar iniciativas que impulsen el crecimiento de la empresa y el bienestar de los colaboradores.Implementar estrategias de mejora, elaborando procedimientos y estandarizando procesos, asegurando su cumplimiento en todas las áreas.Realizar el proceso de selección de personal end to end: publicación de avisos, filtrado de candidatos y presentación de la terna final.Participar en la organización de eventos internos.Colaborar en el diseño de piezas comunicacionales.RequisitosLicenciatura en Recursos Humanos o Relaciones Laborales (excluyente).Experiencia no menor a 5 años en RRHH (excluyente).Manejo avanzado de Excel.Conocimiento de legislación laboral.Experiencia en administración de personal: altas, bajas, modificaciones y control de novedades para liquidación de sueldos (excluyente).Condiciones de trabajoLugar: MicrocentroJornada laboral:Lunes a viernes de 11:00 a 19:00 hs (presencial).Sábados de 9:00 a 16:00 hs (home office).Si te interesa el desafío y tenés ganas, actitud y proactividad¡Te esperamos para ser parte de este gran equipo!",
    "requirements": "Educación mínima: Universitario5 años de experiencia"
}