{
    "title": "Analista de logística - Permanente",
    "business_name": "ManpowerGroup",
    "location": "Neuquen, Neuquén",
    "description": "ANALISTA DE LOGÍSTICA  (n° Req 200462)  PERMANENTEEstamos seleccionando para Importante empresa líder en Servicios de logística y transporteZona de Trabajo: Neuquén CapitalJornada Laboral: De lun a vie de 14:00 a 22:00 hs Sábados de 8 a 12 hs.Esquema de Empleo: PresencialModalidad de Contratación: PermanenteSe Ofrece:Banda salarial acorde a la posición y mercado.Solidas oportunidades de crecimiento.Incorporación a una empresa en crecimiento, con valores sólidos y cultura orientada a la innovación.Las principales funciones del puesto serán:Supervisar las operaciones diarias de transporte y cierre de rutas, coordinando con choferes y equipos operativos.Autorizar y controlar RTS, gestionar incidencias y asegurar el correcto uso de herramientas de gestión.Planificar y ejecutar inventarios, analizando divergencias y asegurando la precisión de los registros.Monitorear KPIs logísticos, detectar oportunidades de mejora y proponer acciones correctivas.Controlar devoluciones y gestionar la calidad operativa en línea con los estándares establecidos (WOW | GEMBAS).Brindar soporte al equipo de planificación (LM) y coordinar requerimientos de flota o ambulancias cuando sea necesario.Requisitos:Secundario completo (excluyente).Preferentemente estudios terciarios/universitarios en logística, Ingeniería Industrial, Administración, Ciencias Económicas.Experiencia mínima de 2 años en posiciones similares.Manejo eficiente de paquete Office y Google.Habilidades de comunicacion.Licencia de conducir vigente (excluyente)Al postularte o avanzar en este proceso, aceptás el tratamiento de tus datos personales conforme a nuestra Política de Privacidad, en cumplimiento de la Ley 25.326. ManpowerGroup Argentina tratará tu información exclusivamente con fines de evaluación y contacto en relación con oportunidades laborales. Podés ejercer tus derechos de acceso, rectificación o supresión cuando lo desees.En ManpowerGroup promovemos una cultura inclusiva y diversa basada en el respeto y en la igualdad de oportunidades.",
    "requirements": "Educación mínima: Terciario2 años de experiencia"
}