{
    "title": "Asesor comercial",
    "business_name": "Importante empresa del sector",
    "location": "Resistencia, Chaco",
    "description": "Estamos buscando un/a Asesor/a Comercial para sumar a nuestro equipo de Resistencia.La persona seleccionada será responsable de gestionar una cartera de clientes, brindar asesoramiento especializado y garantizar una experiencia de calidad en cada interacción.Responsabilidades principalesIdentificar necesidades y oportunidades en cada cliente, ofreciendo soluciones a medida.Elaborar estrategias de venta basadas en el análisis de datos y tendencias del mercado.Asegurar un alto nivel de satisfacción del cliente y construir relaciones sólidas y sostenibles.RequisitosMínimo 1 año de experiencia en ventas o asesoramiento comercial.Probada capacidad para alcanzar objetivos y generar crecimiento en ventas.Excelentes habilidades de comunicación verbal y escrita.Proactividad, orientación a resultados y capacidad para trabajar bajo presión.Atención al detalle y enfoque en la experiencia del cliente.Si te apasionan los desafíos, el desarrollo comercial y la construcción de vínculos de valor, queremos conocerte.Sumate y acompañanos en el crecimiento continuo de la empresa.",
    "requirements": "Educación mínima: Secundaria1 año de experienciaEdad: entre 25 y 45 añosDisponibilidad de viajar: Si"
}